{
  "id": "cl-leychile-norma-27808",
  "type": "statute",
  "title": "MODIFICA EL ARTICULO 1°, SUSTITUYE LA LETRA B) Y\nAGREGA LETRAS G) Y H) AL ARTICULO 5° DE LA LEY 13.331,\nDE 22 DE JULIO DE 1959, QUE AUTORIZO A LA MUNICIPALIDAD\nDE QUINTERO PARA CONTRATAR PRESTAMOS POR LA CANTIDAD QUE\nINDICA, CON EL FIN DE INVERTIRLOS EN DIVERSAS OBRAS DE\nADELANTO LOCAL.",
  "short_name": "Ley 14615",
  "status": "in_force",
  "issued_date": "1961-08-31",
  "in_force_date": "1961-09-12",
  "url": "https://www.bcn.cl/leychile/navegar?idNorma=27808",
  "provisions": [
    {
      "provision_ref": "artunico",
      "section": "UNICO",
      "title": "Artículo UNICO",
      "content": "\"Artículo único. Introdúcense las siguientes modificaciones a la ley 13.331, de fecha 22 de julio de 1959:\n1) Substitúyese en el artículo 1°, la suma de \"$ 40.000.000\" por E° 50.000\".\n2) Substitúyese la letra b) del artículo 5°, por la siguiente:\n\"b) Construcción de un Mercado Municipal ____ E° 8.000\"\n3) Agrégase al artículo 5°, las\nsiguientes letras nuevas:\n\"g) Obras de alumbrado público ______________ E° 8.000\nh) Aporte para la compra de una máquina\nmotoniveladora __________________________ 2.000\""
    }
  ],
  "definitions": []
}