{
  "id": "cl-leychile-norma-26713",
  "type": "statute",
  "title": "MODIFICA EL ARTICULO 2.o TRANSITORIO DE LA LEY N.o\n10,583",
  "short_name": "Ley 11571",
  "status": "in_force",
  "issued_date": "1954-08-09",
  "in_force_date": "1954-08-24",
  "url": "https://www.bcn.cl/leychile/navegar?idNorma=26713",
  "provisions": [
    {
      "provision_ref": "artunico",
      "section": "UNICO",
      "title": "Artículo UNICO",
      "content": "\"Artículo único. Reemplázase el artículo 2.o transitorio de la ley N.o 10,583, actual artículo 1.o transitorio de la ley N.o 11,469, por el siguiente:\n\"Para los efectos de la aplicación de la ley N.o 10.583, en lo que se refiere al pago de sueldos, jornales y gratificaciones, no regirán, durante los años 1952, 1953, 1954, 1955, 1956 y 1957, las limitaciones contempladas en los artículos 32.o y 35.o de la ley sobre Estatuto de los Empleados Municipales de la República y artículo 109 de la Ley de Organización y Atribuciones de las Municipalidades.\nDurante la vigencia de la presente ley no podrán crearse nuevos cargos ni contratarse nuevo personal en exceso del que exista a la fecha de esta ley\"."
    }
  ],
  "definitions": []
}