{
  "id": "cl-leychile-norma-227992",
  "type": "statute",
  "title": "CONCEDE PENSION, POR GRACIA, A DOÑA ROSA ELENA ROJAS\nVIUDA DE GUERRA Y A SU HIJA DOÑA TEGUALDA GUERRA ROJAS",
  "short_name": "Ley 17241",
  "status": "in_force",
  "issued_date": "1969-11-14",
  "in_force_date": "1969-11-21",
  "url": "https://www.bcn.cl/leychile/navegar?idNorma=227992",
  "provisions": [
    {
      "provision_ref": "artunico",
      "section": "UNICO",
      "title": "Artículo UNICO",
      "content": "Artículo único.- Concédese, por gracia, a doña Rosa Elena Rojas viuda de Guerra y a su hija, doña Tegualda Guerra Rojas, una pensión de Eº 75 mensuales para cada una, con derecho de acrecer entre ellas.\nEl gasto que demande el cumplimiento de la presente ley se imputará al ítem de Pensiones del presupuesto del Ministerio de Hacienda."
    }
  ],
  "definitions": []
}