{
  "id": "cl-leychile-norma-28546",
  "type": "statute",
  "title": "MODIFICA LA APLICACION DEL ARTICULO 6°. DE LA LEY\nNUMERO 16.464",
  "short_name": "Ley 16577",
  "status": "in_force",
  "issued_date": "1966-10-11",
  "in_force_date": "1966-10-28",
  "url": "https://www.bcn.cl/leychile/navegar?idNorma=28546",
  "provisions": [
    {
      "provision_ref": "art1",
      "section": "1",
      "title": "Artículo 1",
      "content": "\"Artículo único.- No será aplicable lo dispuesto en el inciso primero del artículo 6°. de la ley número 16.464, de 25 de Abril de 1966, a los empleados y obreros municipales que, a contar desde el 1°. de Enero del mismo año, se les haya otorgado o aumentado la asignación de estímulo que las Municipalidades hubieren concedido, en virtud de lo establecido en el artículo 1°. de la ley N°. 13.195, de 31 de Octubre de 1958.\""
    }
  ],
  "definitions": []
}