{
  "id": "cl-leychile-norma-25658",
  "type": "statute",
  "title": "INCORPORA EL DEPARTAMENTO DE TALAGANTE, PARA LOS\nEFECTOS DE LA ELECCION DE DIPUTADOS, AL SEGUNDO DISTRITO\nDEL DEPARTAMENTO DE SANTIAGO.",
  "short_name": "Ley 7823",
  "status": "in_force",
  "issued_date": "1944-08-16",
  "in_force_date": "1944-08-31",
  "url": "https://www.bcn.cl/leychile/navegar?idNorma=25658",
  "provisions": [
    {
      "provision_ref": "artunico",
      "section": "UNICO",
      "title": "Artículo UNICO",
      "content": "\"Artículo único. Declárase que, para los efectos de la elección de Diputados, los territorios comunales que forman el departamento de Talagante se considerarán incorporados al Segundo Distrito del departamento de Santiago.\nEsta ley regirá desde la fecha de su publicación en el Diario Oficial\"."
    }
  ],
  "definitions": []
}