{
  "id": "cl-leychile-norma-232320",
  "type": "statute",
  "title": "CONCEDE PENSION, POR GRACIA, A DOÑA LUISA OYARZUN VIUDA\nDE SALAS",
  "short_name": "Ley 16329",
  "status": "in_force",
  "issued_date": "1965-09-23",
  "in_force_date": "1965-10-05",
  "url": "https://www.bcn.cl/leychile/navegar?idNorma=232320",
  "provisions": [
    {
      "provision_ref": "artunico",
      "section": "UNICO",
      "title": "Artículo UNICO",
      "content": "Artículo único.- Concédese, por gracia, a doña Luisa Oyarzún viuda de Salas, una pensión de Eº 30 mensuales.\nEl gasto que demande esta ley se imputará al ítem de Pensiones del Presupuesto del Ministerio de Hacienda."
    }
  ],
  "definitions": []
}