{
  "id": "cl-leychile-norma-23459",
  "type": "statute",
  "title": "Concede una asignación anual al Profesor don Miguel;Luis Amunátegui Reyes.",
  "short_name": "Ley 2738",
  "status": "in_force",
  "issued_date": "1913-01-10",
  "in_force_date": "1913-01-14",
  "url": "https://www.bcn.cl/leychile/navegar?idNorma=23459",
  "provisions": [
    {
      "provision_ref": "artunico",
      "section": "UNICO",
      "title": "Artículo UNICO",
      "content": "Artículo único.- En atencion a los servicios prestados a la instruccion pública por don Miguel Luis Amunátegui Reyes, concédesele, por gracia, una asignacion de tres mil quinientos pesos anuales, que gozará sin perjuicio de la pension que le corresponde por su jubilacion."
    }
  ],
  "definitions": []
}