{
  "id": "cl-leychile-norma-137360",
  "type": "statute",
  "title": "MODIFICA LA LEY Nº 15.378",
  "short_name": "Ley 16931",
  "status": "in_force",
  "issued_date": "1968-09-02",
  "in_force_date": "1968-09-10",
  "url": "https://www.bcn.cl/leychile/navegar?idNorma=137360",
  "provisions": [
    {
      "provision_ref": "artunico",
      "section": "UNICO",
      "title": "Artículo UNICO",
      "content": "\"Artículo único.- Reemplázanse en el artículo 3º de la ley Nº 15.378, de 18 de Diciembre de 1963, las palabras \"por el DFL. Nº 81, de 1960, de la escala de grados y sueldos del Cuerpo de Carabineros de Chile\" por estas otras: \"en el artículo 1º, letra a), de la ley Nº 11.852, de 29 de Agosto de 1955.\".\""
    }
  ],
  "definitions": []
}