{
  "id": "cl-leychile-norma-241054",
  "type": "statute",
  "title": "AUMENTA, POR GRACIA, LA PENSION DE DOÑA ERNESTINA\nMARTINEZ VIUDA DE BRAVO",
  "short_name": "Ley 15605",
  "status": "in_force",
  "issued_date": "1964-07-08",
  "in_force_date": "1964-07-23",
  "url": "https://www.bcn.cl/leychile/navegar?idNorma=241054",
  "provisions": [
    {
      "provision_ref": "artunico",
      "section": "UNICO",
      "title": "Artículo UNICO",
      "content": "Artículo único.- Auméntase, por gracia, a Eº 60 mensuales, la pensión de que disfruta doña Ernestina Martínez viuda de Bravo.\nEl gasto que demande esta ley se imputará al ítem de pensiones del presupuesto del Ministerio de Hacienda."
    }
  ],
  "definitions": []
}