{
  "id": "cl-leychile-norma-285974",
  "type": "statute",
  "title": "ABONA POR GRACIA EL TIEMPO QUE INDICA A DON JULIO\nBRAVO HAYLEY",
  "short_name": "Ley 11495",
  "status": "in_force",
  "issued_date": "1954-01-20",
  "in_force_date": "1954-02-05",
  "url": "https://www.bcn.cl/leychile/navegar?idNorma=285974",
  "provisions": [
    {
      "provision_ref": "artunico",
      "section": "UNICO",
      "title": "Artículo UNICO",
      "content": "Artículo único. Abónase, por gracia y para todos los efectos legales, en la hoja de servicios del ex Jefe de la Sección Pensiones del Ejército, don Julio Bravo Hayley, 2 meses y 2 días, que le servirán para completar el tiempo que exige el inciso tercero del artículo 56 de la ley N.o 10,343, de 28 de Mayo de 1952, sin perjuicio de los beneficios que otras leyes otorguen o puedan otorgar a los empleados civiles del Ministerio de Defensa Nacional, debiendo reajustarse su pensión de retiro o la de montepío en su oportunidad, bajo las bases indicadas.\nEl mayor gasto que importe esta ley se imputará al ítem de pensiones del presupuesto del Ministerio de Hacienda."
    }
  ],
  "definitions": []
}