{
  "id": "cl-leychile-norma-27303",
  "type": "statute",
  "title": "AUTORIZA A LA MUNICIPALIDAD RENAICO PARA\nSUPLEMENTAR, EN LA CANTIDAD QUE INDICA, SU PRESUPUESTO\nDE EGRESOS ODINARIOS.",
  "short_name": "Ley 12946",
  "status": "in_force",
  "issued_date": "1958-08-20",
  "in_force_date": "1958-08-28",
  "url": "https://www.bcn.cl/leychile/navegar?idNorma=27303",
  "provisions": [
    {
      "provision_ref": "artunico",
      "section": "UNICO",
      "title": "Artículo UNICO",
      "content": "\"Artículo único. Autorízase a la Municipalidad de Renaico para que suplemente el ítem 24-c \"Alumbrado Público y Dependencias\" de su presupuesto de Egresos Ordinarios vigente, en la cantidad de $ 528.165, saldo actualmente ampozado en la Tesorería Comunal de Renaico y proveniente de la contribución del uno y medio por mil sobre el avalúo de los bienes raíces de la comuna de Renaico, establecida en el artícuo 5° de la ley 10.043, de 6 de noviembre de 1951, quedando como remanente después de pagado el empréstito que autorizó dicha ley.\""
    }
  ],
  "definitions": []
}