{
  "id": "cl-leychile-norma-29105",
  "type": "statute",
  "title": "CONCEDE AMNISTIA A LAS PERSONAS QUE INDICA",
  "short_name": "Ley 17553",
  "status": "in_force",
  "issued_date": "1971-10-28",
  "in_force_date": "1971-11-12",
  "url": "https://www.bcn.cl/leychile/navegar?idNorma=29105",
  "provisions": [
    {
      "provision_ref": "artunico",
      "section": "UNICO",
      "title": "Artículo UNICO",
      "content": "\"Artículo único.- Concédese amnistía a los Alcaldes, Regidores, funcionarios municipales, ex Alcaldes y ex Regidores que arbitrariamente hayan dado a los caudales o efectos municipales que administran o administraron una aplicación pública diferente de aquélla a que estaban destinados.\nLa amnistía comprende, tambien, los delitos en que hubieren incurrido como medios necesarios para llevar a cabo la aplicación pública arbitraria de dichos caudales o efectos; pero en caso alguno favorecerá a quienes hubieren delinquido por lucro personal o de terceros o aplicando esos caudales o efectos a usos propios o ajenos.\nLa amnistía beneficiará a los Tesoreros Comunales o Provinciales y demás personas penalmente responsables por su participación en los hechos a que se refieren los incisos anteriores.\nEl sobreseimiento o absolución que se dictare en virtud de esta ley, deberá siempre consultarse.\nEn todo caso, la amnistía sólo se extiende a la responsabilidad penal derivada de hechos acaecidos con anterioridad al 1° de julio de 1971.\"."
    }
  ],
  "definitions": []
}