{
  "id": "cl-leychile-norma-29297",
  "type": "statute",
  "title": "AUTORIZA A S.E. EL PRESIDENTE DE LA REPUBLICA PARA\nTRANSFERIR GRATUITAMENTE EL PREDIO FISCAL QUE SEÑALA",
  "short_name": "Ley 17810",
  "status": "in_force",
  "issued_date": "1972-10-30",
  "in_force_date": "1972-11-10",
  "url": "https://www.bcn.cl/leychile/navegar?idNorma=29297",
  "provisions": [
    {
      "provision_ref": "artunico",
      "section": "UNICO",
      "title": "Artículo UNICO",
      "content": "\"Artículo único\".- Facúltase al Presidente de la República para transferir gratuitamente a la Municipalidad de Lautaro, un predio fiscal que figura bajo el Rol N° 164-10, sitios N.°s 1 y 2 de la manzana N° 32 de la ciudad de Lautaro.\nLa Municipalidad de Lautaro, por acuerdo de los dos tercios de sus Regidores en ejercicio, podrá asignar en propiedad y sin costo alguno, a sus obreros dichos terrenos, siempre que sean destinados, exclusivamente, a viviendas.\"."
    }
  ],
  "definitions": []
}