{
  "id": "cl-leychile-norma-24309",
  "type": "statute",
  "title": "LEI NUM. 3,869, QUE APRUEBA EL PRESUPUESTO DE ENTRADAS I GASTOS DEL FERROCARRIL DE PUENTE ALTO AL VOLCAN PARA EL AÑO 1922",
  "short_name": "Ley 3869",
  "status": "in_force",
  "issued_date": "1922-07-13",
  "in_force_date": "1922-07-13",
  "url": "https://www.bcn.cl/leychile/navegar?idNorma=24309",
  "provisions": [
    {
      "provision_ref": "artunico",
      "section": "UNICO",
      "title": "Artículo UNICO",
      "content": "ARTICULO UNICO.- Apruébase el siguiente Presupuesto de Entradas i Gastos del Ferrocarril de Puente Alto al Volcan, calculado para el presente año:\nENTRADAS:\nEntradas probables en el año 1922________ $ 400,000.-\nGASTOS\nPartida 1.a\nADMINISTRACION\nItem.\n1 Gratificacion de un Jefe a\n$ 4.00 i 13 Oficiales a $ 4.00\ndiarios_______________________ $ 20,440.-\n2 Sueldo del Injeniero Contador\nTécnico_______________________ 10,000.-\n3 Arriendo de oficinas, teléfono\ni gastos de oficina___________ 4,860.- $ 35,300.-\nPartida 2.a\nVIA I OBRAS NUEVAS\n4 Sueldo de un caminero mayor 3,750.-\n5 Seis cabos de cuadrillas a\n$ 6.25 i 46 jornaleros a\n$ 3.75 diarios________________ $ 71.175.-\n6 Material de enrieladura_____ 3,500.-\n7 10,000 durmientes de pellin\na $ 2.50 c/u__________________ 25,000.-\n8 Carbon i aceite en lastreamiento\nde la via_____________________ 1,000.-\n9 Conservacion de la línea\ntelefónica, postes, aisladores,\netc___________________________ 500.-\n10 Conservacion del cierro de\nla via________________________ 500.-\n11 Reparacion de edificios,\nnuevas construcciones, obras de\nornato, plantaciones, aguadas,\netc___________________________ 30,000.- $ 135,425.-\nPartida 3.a\nTRACCION I LOCOMOTORAS\n12 Gratificacion de maquinistas,\nfogoneros i personal de\nMaestranzas___________________ $ 3,500.-\n13 Jornales de un calderero, un\ntornero, un herrero i un\nfundidor a $ 312.50 c/u mensual 15,000.-\n14 650 toneladas de carbon de\npiedra a $ 140.00 tonelada 91,000.-\n15 2,000 litros de aceite a\n$ 1.20 i 1,000 kilos de hilachas\na $ 2.00 kilo_________________ 4,400.-\n16 Materiales de reposicion i\nnuevas maquinarias____________ 30,000.-\n17 Servicio del automóvil_____ 5,000.- $ 148,900.-\nPartida 4.a\nMOVIMIENTO\n18 Gratificacion de conductores,\nguarda equipajes i palanqueros $ 1,875.-\n19 Alumbrado de trenes________ 400.-\n20 2,500 litros de aceite a $ 1.20\nc/u i 300 kilos de hilachas a\n$ 2.50 c/u____________________ 3,750.-\n21 Materiales, banderolas,\nfaroles, etc__________________ 300.- $ 6,325.-\nPartida 5.a\nTRAFICO\n22 Gratificacion a jefes de\nEstaciones, guarda equipajes i\ncambiadores___________________ $ 5.664.40\n23 Cargadores_________________ 4,000.-\n24 Gratificacion al Jefe de\nEstacion de Puente Alto (F. C.\nLlano de Maipo)_______________ 600.-\n25 Alumbrado de estaciones____ 725.-\n26 Avisos_____________________ 400.-\n27 Boletos, itinerarios,\nformularios, etc______________ 3,300.- $ 14,689.40\nPartida 6.a\nIMPREVISTOS\n28 Imprevistos________________ $ 20,000.- $ 20,000.-\n__________\nTotal__________ $ 360,639.40"
    }
  ],
  "definitions": []
}