{
  "id": "cl-leychile-norma-23482",
  "type": "statute",
  "title": "CONCEDE FONDOS PARA CUBRIR EL MAYOR GASTO OCASIONADO EN ALGUNOS SERVICIOS DEL EJERCITO DURANTE EL AÑO 1912.",
  "short_name": "Ley 2770",
  "status": "in_force",
  "issued_date": "1913-02-11",
  "in_force_date": "1913-02-12",
  "url": "https://www.bcn.cl/leychile/navegar?idNorma=23482",
  "provisions": [
    {
      "provision_ref": "artunico",
      "section": "UNICO",
      "title": "Artículo UNICO",
      "content": "ARTICULO UNICO.- Se autoriza al Presidente de la República para invertir hasta la cantidad de quinientos mil pesos ($ 500,000), en cubrir el mayor gasto que ha ocasionado en 1912 la atencion de los servicios de forraje, talaje i sal para el ganado del Ejércio, carretonaje i adquisicion de carros para el trasporte de forraje, paja para colchones de tropa i cama para el ganado i forraje en especies i en dinero para los oficiales del Ejército en conformidad a la lei de sueldos vijente."
    }
  ],
  "definitions": []
}