{
  "id": "cl-leychile-norma-26437",
  "type": "statute",
  "title": "FIJA EXCEPCIONES EN LA APLICACION DE LA LEY N.o\n10,254, RELACIONADA CON VENTA DE SITIOS POR LA CAJA DE\nLA HABITACION.",
  "short_name": "Ley 10541",
  "status": "in_force",
  "issued_date": "1952-09-16",
  "in_force_date": "1952-10-02",
  "url": "https://www.bcn.cl/leychile/navegar?idNorma=26437",
  "provisions": [
    {
      "provision_ref": "artunico",
      "section": "UNICO",
      "title": "Artículo UNICO",
      "content": "Artículo único. Las disposiciones de los artículos 17 y siguientes de la ley N.o 10,254, de 4 de Febrero último, no se aplicarán a las ventas de sitios que se hagan conformes a un plano aprobado a virtud de acuerdo de la Municipalidad respectiva, adoptado con anterioridad a la dictación de esa ley."
    }
  ],
  "definitions": []
}