{
  "id": "cl-leychile-norma-28824",
  "type": "statute",
  "title": "OTORGA DERECHO A HACER IMPOSICIONES QUE INDICA A\nFUNCIONARIOS DE REGISTRO CIVIL E IDENTIFICACION QUE\nSEÑALA",
  "short_name": "Ley 17183",
  "status": "repealed",
  "issued_date": "1969-09-09",
  "in_force_date": "1984-12-28",
  "url": "https://www.bcn.cl/leychile/navegar?idNorma=28824",
  "provisions": [
    {
      "provision_ref": "artunico",
      "section": "UNICO",
      "title": "Artículo UNICO",
      "content": "\"Artículo único.- Los funcionarios de la Quinta\nCategoría y Categorías superiores a ésta de la Planta\nDirectiva, Profesional y Técnica del Servicio de\nRegistro Civil e Identificación podrán, para todos los\nefectos legales, ejercer el derecho que contempla el\nartículo 61 del DFL. N.° 1.340 bis, de 6 de Agosto de 1930, aun cuando sólo perciba las remuneraciones asignadas al cargo que desempeñen, limitándose la declaración a un 50% de estas últimas que fueren imponibles.\nLas imposiciones que corresponda efectuar para ejercer el derecho que se concede en el inciso anterior, no podrán ser cobradas por las Cajas de Previsión respectivas con efecto retroactivo, sino a contar de la fecha en que dicho derecho sea declarado por el funcionario.\"."
    }
  ],
  "definitions": []
}