{
  "id": "cl-leychile-norma-30732",
  "type": "statute",
  "title": "MODIFICA DISTRIBUCION DE CARGOS QUE SE CREAN EN LAS\nPLANTAS DE PERSONAL DEL SECTOR SALUD POR LA LEY N°\n19.308",
  "short_name": "Ley 19365",
  "status": "in_force",
  "issued_date": "1994-12-26",
  "in_force_date": "1994-12-31",
  "url": "https://www.bcn.cl/leychile/navegar?idNorma=30732",
  "provisions": [
    {
      "provision_ref": "artunico",
      "section": "UNICO",
      "title": "Artículo UNICO",
      "content": "\"Artículo único.- Modifícase, a contar de la fecha de su vigencia, la ley N° 19.308, en la siguiente forma:\na) Sustitúyese el cuadro de distribución de cargos establecido en el inciso primero de su artículo 1°, por el siguiente:\nCREACION DE CARGOS EN LAS PLANTAS QUE SE INDICAN\n_______________________________________________________\n| NOTA: VER DIARIO OFICIAL N° 35.055 DEL DIA SABADO |\n| 31 DE DICIEMBRE DE 1994, PAGINAS 2 Y 3. |\n|_____________________________________________________|\nb) Sustitúyese en el inciso final del artículo 2°, el guarismo \"seis\" por \"diez\".\"."
    }
  ],
  "definitions": []
}