{
  "id": "cl-leychile-norma-135537",
  "type": "statute",
  "title": "",
  "short_name": "Ley 1581",
  "status": "repealed",
  "issued_date": "1903-01-13",
  "in_force_date": "1930-02-11",
  "url": "https://www.bcn.cl/leychile/navegar?idNorma=135537",
  "provisions": [
    {
      "provision_ref": "artunico",
      "section": "UNICO",
      "title": "Artículo UNICO",
      "content": "Artículo único.- Prorrógase por un nuevo período de diez años, a contar desde el 20 de enero de 1903, la prohibicion de adquirir terrenos de indíjenas, contenida en el artículo 6.º de la lei de 4 de agosto de 1874 i en las leyes de 20 de enero de 1883 i 11 de enero de 1893."
    }
  ],
  "definitions": []
}