{
  "id": "cl-leychile-norma-25864",
  "type": "statute",
  "title": "TRASPASA DIVERSAS CANTIDADES ENTRE LOS ITEM QUE\nMENCIONA DEL PRESUPUESTO VIGENTE",
  "short_name": "Ley 8923",
  "status": "in_force",
  "issued_date": "1947-11-14",
  "in_force_date": "1947-11-15",
  "url": "https://www.bcn.cl/leychile/navegar?idNorma=25864",
  "provisions": [
    {
      "provision_ref": "art1",
      "section": "1",
      "title": "Artículo 1",
      "content": "Artículo 1.o Transpásanse las cantidades que se indican entre los siguientes ítem del presupuesto vigente:\n-------------------------------------------------------\nDE LOS ITEM\nPresidencia de la República.\n01/01/01 Sueldos fijos____ 72.000.-\n01/01/02/e-1) Asignación\nfamiliar_________ 6.500.-\n01/01/02/e-2) Asignación\nfamiliar personal\nasimilado a\nCarabineros______ 12.000.-\n01/01/12 Planta\nsuplementaria____ 51.660.-$142.160.-\nConsejo de Defensa Fiscal.\n03/02/01 Sueldos fijos____ 41.750.-\n03/02/02/a Por años de\nservicio_________ 14.250.- 56.000.-\nMINISTERIO DEL INTERIOR\nSubsecretaría.\n04/01/01 Sueldos fijos____ 36.500.- 36.500.-\nCorreos y Telégrafos.\n04/03/04/f-2-2) Pasajes y fletes\nen empresas\nprivadas_________ 120.000.-\n04/03/12 Planta\nsuplementaria__1.344.000.-1.464.000.-\nDirección General del Registro Electoral.\n04/04/04/j-2 Publicaciones en\ndiarios y\nrevistas\nmotivadas por\nlas elecciones\nmunicipales______ 200.000.-\n04/04/04/j-3 Publicaciones en\ndiarios y\nrevistas,\nelecciones\nextraordinarias\ncongresales______ 300.000.- 500.000.-\nDirección General de Auxilio Social.\n04/05/04/c Viáticos_________ 10.000.-\n04/05/04/1 Conservación y\nreparaciones_____ 5.000.-\n04/05/04/w Adquisiciones____ 10.000.- 25.000.-\nDirección General de Carabineros.\n04/06/01 Sueldos fijos___3.500.000.-\n04/06/11/a-2 Para completar el\nservicio de los\npréstamos\ncontratados en\nconformidad a la\nley 6,044_______330.000.-3.830.000.-\nDirección General de Investigaciones.\n04/07/01 Sueldos fijos___1.643.895.-\n04/07/02/b Por residencia en\nciertas zonas____ 241.081.-\n04/07/02/e Asignación\nfamiliar_________389.306.-2.274.282.-\nDirección General de Servicios Eléctricos.\n04/08/04/b Gratificaciones y\npremios__________ 21.500.-\n04/08/12 Planta\nsuplementaria____ 132.400.- 153.900.-\nDirección General de Agua Potable y\nAlcantarillado.\n04/10/01 Sueldos fijos____ 222.300.-\n04/10/02/e Asignación\nfamiliar_________ 28.800.-\n04/10/04/a-2 Para pago\nreemplazantes\nempleados que\nhagan uso feriado\nlegal____________ 150.000.-\n\" b-2 Asignación por\npérdida de caja__ 3.000.-\n\" b-3 Asignación\nfamiliar\nempleados y\nobreros__________ 10.000.-\n\" e Arriendo de bienes\nraíces___________ 40.000.-\n\" p Previsión y\npatentes_________ 40.000.-\n04/10/11/a-6 Construcción de\nuniones e\ninstalaciones\ndomiciliarias agua\npotable y\nalcantarillado___ 50.000.-\n04/10/12 Planta\nsuplementaria____ 295.000.- 839.100.-\nDirección General de Informaciones y\nCultura.\n04/11/01 Sueldos fijos____ 203.733.-\n04/11/12 Planta\nsuplementaria____ 36.600.- 240.333.-\nMINISTERIO DE RELACIONES EXTERIORES\nSubsecretaría.\n05/01/04/v-9-a Imprenta \"La\nNación\" por\nimpresiones______ 71.829.-\n\" v-9-a Compañía de\nCables___________ 1.773.- 73.602.-\nServicio Exterior (Presupuesto oro):\n05/02/04/a-3 Pago de\nemolumentos al\nrepresentante de\nChile en Río de\nJaneiro (oro\n52,569)__________ 210.276.-\n05/02/04/b-1 Para pago de\nexpensas de\nestablecimiento\n(oro 90,000)_____ 360.000.-\n\" b-3 Gasto\nrepresentación\nEncargado de\nNegocios ad\ninterim (oro 409) 1.636.-\n\" k-2 Auxilio de\nchilenos en el\nextranjero (oro\n30.000)__________ 120.000.-\n\" v-1 Suplencias\npersonal\ndiplomático\nconsular (oro\n20,000)__________ 80.000.-\n\" v-9 Gastos derivados\nde compromisos\ninternacionales\n(oro 250,000)___1.000.000.-\n\" v-15 Para dar\ncumplimiento a la\nley 5,457 (oro\n20,500)__________ 82.000.-\n\" v-18-d Instituto\nInternacional de\nAgricultura de\nRoma (oro\n120,082)_________ 480.328.-\n\" v-18-e Comisión\nPanamericana de\nCooperación\nIntermunicipal\n(oro 1,996)______ 7.984.-\n\" v-18-f Organismo de\nAlimentación de\nlas Naciones\nUnidas (oro\n290,572)________1.162.288.-\n\" v-18-g Organización\nProvisoria de la\nAviación Civil\nInternacional\n(oro 91,439)_____ 365.756.-\n\" w Adquisiciones\n(oro 20,000)_____80.000.- 3.950.268.-\nMINISTERIO DE HACIENDA\nSubsecretaría.\n06/01/05/b-5 Para atender al\npago de otras\ndeudas\nflotantes__$22.300.000.-$22.300.000.-\nSuperintendencia de Aduanas.\n06/05/04/b-3 Para pago de\ntrabajos\nextraordinarios__ 100.000.-\n\" v-1 Arriendo\nmáquinas\nHollerith________ 100.000.- 200.000.-\nTesorería General de la República\n06/06/04/v-1 Imprevistos______ 20.000.-\n\" v-4 Reemplazo de\npersonal que\ncumple Servicio\nMilitar__________ 95.000.- 115.000.-\nSuperintendencia de la Casa de Moneda y Especies\nValoradas.\n06/07/02/a Por años de\nservicio_________ 10.000.- 10.000.-\nSuperintendencia de Cías. de Seguros, etc.\n06/10/01 Sueldos fijos____ 36.000.- 36.000.-\nMINISTERIO DE EDUCACION PUBLICA\nDirección General de Educación Secundaria.\n07/03/02/a Por años de\nservicio (Liceos\nde\nexperimentación 1.020.000.-\n07/03/04/e Arriendo de\nbienes raíces___ 300.000.-\n\" y-10 sobresueldos\nprofesores que\ndesempeñen\nfunciones de\nconsejeros\nvocacionales_____ 45.000.-\n07/03/04/v-11 Profesores\nsuplentes Liceos\nExperimentales___ 25.000.-1.390.000.-\nMINISTERIO DE JUSTICIA\nTribunales Superiores de Justicia:\n08/02/01 Sueldos fijos____ 125.000.-\n08/02/02 e Asignación\nfamiliar_________ 30.000.-$155.000.-\nJuzgados de Letras de Mayor Cuantía:\n08/03/01 Sueldos fijos____ 260.000.-\n08/03/02 e Asignación\nfamiliar_________ 260.000.- 520.000.-\nJuzgados de Letras de Menor Cuantía:\n08/04/01 Sueldos fijos____ 30.000.-\n08/04/02 e Asignación\nfamiliar_________ 30.000.- 60.000.-\nDirección General del Registro Civil:\n08/05/01 Sueldos fijos____ 350.000.-\n08/05/02 e Asignación\nfamiliar_________ 450.000.- 800.000.-\nInstituto Médico-Legal Dr. Carls Ibar\ny médicos legistas:\n08/07/04 e Arriendo de\nbienes raíces____ 10.000.-\n08/07/04 w Adquisiciones____ 10.000.- 20.000.-\nDirección General de Prisiones:\n08/08/01 Sueldos fijos____ 800.000.-\n08/08/02 e Asignación\nfamiliar_________ 80.000.-\n08/08/04 v-8 Instalación y\ndotación Cárcel\nde Curacautín___ 100.000.-\n08/08/11 a Obras Públicas__ 350.000.-\n08/08/12 Planta\nSuplementaria____380.000.-1.710.000.-\nMINISTERIO DE DEFENSA NACIONAL\nSubsecretaría de Guerra:\n09/01/01 Sueldos fijos__10.087.234.-\n09/01/01 a-1 Quinquenios______ 879.947.-\n\" a-2 10, 15 y 20 %\nderecho a subir\nde grado empleados\nciviles__________ 2.517.-\n\" a-3 20 y 30 % para\nlos brigadieres\nque cumplan 5 y\n10 años en el\nmismo empleo_____ 135.465.-\n\" f-2 Gratificación de\nordenanza________ 704.552.-\n\" f-3 Remuneración de\nprofesorado civil\nmilitar__________ 277.055.-\n09/01/04 v-4 Subsidio de 10\nalféreces_______108.000.-12.194.770.-\nSubsecretaría de Marina:\n10/01/01 Sueldos fijos__6.110.000.-6.110.000.-\nSubsecretaría de Aviación:\n11/01/01 Sueldos fijos__ 3.900.000.-\n11/01/02 a-1 Sobresueldos 20 %\nsuboficiales\nmayores__________ 20.000.-\n\" a-3 10, 15, y 20 %\npara los empleados\nciviles de la\nFACH_____________ 31.000.-\n11/01/02/a-4 20 % personal de\nMaestranza de la\nFACH que tengan\nmás de 10 años\nde servicio______ 327.000.-\n\" v Por residencia en\nciertas zonas____ 200.000.-\n\" f-2 Gratificación de\nordenanza________ 120.000.-\n\" f-3 Gratificación de\nvuelo____________ 35.000.-\n11/01/04 v-5-a Pago derecho de\ninternación_____ 490.000.-5.123.000.-\nMINISTERIO DE OBRAS PUBLICAS\nSubsecretaría:\n12/01/04 v-7 Para reembolsar a\nChilian Northern\nRailway Co. Ltd__ 250.000.- 250.000.-\n___________\nMINISTERIO DE AGRICULTURA\nSubsecretaría:\n13/01/04 e-1 Arriendo\nSubsecretaría___ 76.100.-\n13/01/12 Planta\nsuplementaria____ 111.000.- 187.100.-\n__________\nDirección General de Agricultura:\n13/02/12 Planta\nsuplementaria____ 492.900.- 492.900.-\n__________\nMINISTERIO DE TIERRAS Y COLONIZACION\n14/02/04 v-4 Auxilio Colonias\nAgrícolas en\nterrenos fiscales 400.000.- 400.000.-\n_________\nMINISTERIO DEL TRABAJO\nDirección General del Trabajo\n15/02/01 Sueldos fijos____ 149.525.-\n15/02/02 e Asignación\nfamiliar_________ 210.000.-\n15/02/04 e Arriendo de\nbienes raíces____ 40.000.-\n\" v-2 Pago honorarios\nrepresentantes\nJuntas\nPermanentes de\nConciliación_____ 10.000.-\n\" v-3 Imprevistos______ 20.000.-\n\" v-4 Para dar\ncumplimiento al\nTítulo IX de la\n2.a parte del\ndecreto\nreglamentario\n1,184, del\n10-XII-42________ 5.000.-\n\" v-6 Pago de\nremuneraciones a\nlos 24 vocales de\nlas Cortes del\nTrabajo__________ 30.000.-\n\" v-7 Remunerar a los\nvocales ante las\nCortes del\nTrabajo por fallo\na que concurran__ 60.000.- 524.525.-\n_________\nMINISTERIO DE SALUBRIDAD, PREVISION Y\nASISTENCIA SOCIAL\nSubsecretaría:\n16/01/04 e Arriendo de\nbienes raíces____ 96.000.-\n16/01/12 Planta\nsuplementaria____ 153.300.- 249.300.-\n_________\nDirección General de Sanidad\n16/02/01 Sueldos fijos____ 552.556.-\n16/02/12 Planta\nsuplementaria____ 332.913.- 885.469.-\n_________\nDirección General de Protección a la\nInfancia y Adolescencia:\n16/03/01 Sueldos fijos____ 172.500.-\n16/03/02 f Por otros\nconceptos________ 300.000.-\n16/03/04 b Gratificaciones y\npremios__________ 67.500.- 540.000.-\n_________\nDirección General de Previsión Social:\n16/05/01 Sueldos fijos____ 229.000.-\n16/05/02 e Asignación\nfamiliar_________ 16.000.-\n16/05/04 p Previsión y\npatentes_________ 15.000.-\n\" w Adquisiciones____ 100.000.-\n16/05/12 Planta\nsuplementaria____ 77.000.- 437.000.-\n_________\nMINISTERIO DE ECONOMIA Y COMERCIO\nDepartamento de Minas y Petróleos:\n17/03/04 f-2 Pasajes y fletes\nen empresas\nprivadas_________ 4.000.- 4.000.-\nDepartamento de Pezca y Caza\n17/04/04 j Impresos,\nimpresiones y\npublicaciones____ 12.000.-\n\" v-3 Para selección\nde choros,\ntransportes de\nsemillas y\ncreación de\nbancos___________ 8.000.- 20.000.-\n_________\nDirección General de Estadística:\n17/05/04 1 Conservación y\nreparaciones_____ 27.000.-\n17/05/12 Planta\nsuplementaria____ 150.000.- 177.000.-\n_________\nComisariato General de Subsistencias y\nPrecios:\n17/06/02 b Por residencia en\nciertas zonas____ 102.000.-\n17/06/04 k Gastos generales\nde oficina_______ 10.000.- 112.000.-\n_________\nTOTAL____________ $ 68.608.209.-\nA LOS SIGUIENTES ITEM:\nPresidencia de la República\n01/01/04 g Materiales y\nartículos de\nconsumo__________ 200.000.-\n\" f-1 Pasajes y fletes\nen la Empresa de\nlos FF.CC. del\nEstado___________ 250.000.-\n\" i-1 Rancho o\nalimentación_____ 500.000.-\n01/0104/ i-2 Forraje__________ 5.400.-\n\" i-3 Vestuario y\nequipo __________ 8.600.-\n\" j Impresos,\nimpresiones y\npublicaciones____ 375.000.-\n\" k Gastos generales\nde oficina_______ 45.000.-\n\" m Mantenimiento de\nvehículos\nmotorizados______ 200.000.-\n\" r Consumos de\nelectricidad,\nagua, teléfonos\ny gas____________ 60.000.-\n\" v Varios e\nimprevistos______ 70.000.-\n\" w Adquisiciones____ 30.000.-1.744.000.-\n_______\nSERVICIOS INDEPENDIENTES\nConsejo de Defensa Fiscal:\n03/02/04 b-2 Asignación de\ntraslado_________ 9.250.-\n\" f-1-b Pasajes por vapor 4.000.-\n\" f-2 Pasajes y fletes\nen empresas\nprivadas_________ 4.000.-\n\" j Impresos,\nimpresiones y\npublicaciones____ 25.000.-\n\" k-2 Gastos generales\nde oficina_______ 8.000.-\n\" l Conservación y\nreparaciones_____ 2.000.-\n\" v-1 Gastos Judiciales\ny varios en\nSantiago y\nprovincias_______ 3.750.-$ 56.000.-\n_________\nMINISTERIO DEL INTERIOR\nSubsecretaría:\n04/01/04/b Gratificaciones y\npremios__________ 450.000.-\n\" c-1 Viáticos\nSubsecretaría____ 20.000.-\n\" e Arriendo de\nbienes raíces____ 15.000.-\n\" f-1-a Pasajes por\nferrocarril\nSubsecretaría____ 5.000.-\n\" f-1-b Pasajes por vapor\nSubsecretaría____ 3.000.-\n\" g-1 Materiales y\nartículos de\nconsumo__________ 50.000.-\n\" i-1 Rancho o\nalimentación_____ 10.000.-\n\" j-1 Impresos,\nimpresiones y\npublicaciones____ 140.000.-\n\" k-1 Gastos generales\nde oficina_______ 10.000.-\n\" l-1 Conservación y\nreparaciones_____ 50.000.-\n\" m mantenimiento de\nvehículos\nmotorizados______ 20.000.-\n\" r-2 Agua y teléfonos 20.000.-\n\" v-1 Imprevistos______ 5.000.-\n\" v-3 Gastos\nreservados______300.000.-$1.098.000.-\n____________\nGobierno Interior:\n04/02/04/c Viáticos_________ 50.000.-\n\" f-1-a Pasajes por\nferrocarril______ 120.000.-\n\" f-1-b Pasajes por vapor 50.000.-\n\" f-2 Pasajes y fletes\nen empresas\nprivadas_________ 50.000.-\n\" g Materiales y\nartículos de\nconsumo__________ 50.000.-\n\" i-3 Vestuario y\nequipo___________ 10.000.-\n\" j Impresos,\nimpresiones y\npublicaciones____ 8.000.-\n\" k Gastos generales\nde oficina_______ 10.000.-\n\" l Conservación y\nreparaciones_____ 40.000.-\n\" m Mantenimiento de\nvehículos\nmotorizados______ 50.000.-\n\" r-2 Agua y teléfonos_ 135.000.-\n\" v-1 Imprevistos_____3.075.000.-\n\" v-2 Para el pago de\nIntendentes,\nGobernadores,\nSecretarios de\nGobernación y\notros empleados\nsuplentes ajenos\nal Servicio de\nGobierno Interior,\n(Ley 6,029)______ 300.000.-\n\" w-2 Adquisiciones____ 50.000.-\n\" w-3 Adquisición\nmuebles para\nIntendencias y\nGobernaciones,\n(Intendencia\nÑuble)___________89.793.-$4.087.793.-\n____________\nCorreos y Telégrafos:\n04/03/04/c Viáticos_________ 500.000.-\n\" f-1-b Pasajes por vapor 700.000.-\n\" f-2-l Para el pago de\npasajes y fletes\ny demás gastos\nde movilización\nen otras empresas\nfiscales o en las\nprivadas_________ 74.000.-\n\" g Materiales y\nartículos de\nconsumo__________ 700.000.-\n\" v-2 Para pago de\nsuplencias\ndesempeñadas\nfuera del lugar\nde su residencia.\n(Artículo 58,\nLey 8,282)_______ 70.000.-\n\" w-3 Para la\nadquisición de\ncuatro equipos\nrápidos Siemens\nand Halske\nimpresores,\nusados y\nprovenientes del\nTelégrafo\nComercial________ 63.600.-2.107.600.-\n_________\nDirección del Registro Electoral:\n04/04/04/b-2 Para las\nasignaciones del\nTribunal\nCalificador y\nTribunales\nProvinciales____$ 300.000.-\n\" v-1 Para gastos\nimprevistos\nmotivados por las\nelecciones\ngenerales\nmunicipales______ 200.000.- 500.000.-\n__________\nDirección General de Auxilio\nSocial:\n04/05/04/f-1 Pasajes por\nferrocarriles____ 50.000.-\n\" m Mantenimiento de\nvehículos\nmotorizados______ 25.000.- 75.000.-\n_________\nCarabineros de Chile:\n04/06/04/i-2 Forraje_______$3.230.000.-3.230.000.-\n____________\nDirección General de Investigaciones:\n04/07/04/b-1 Gratificación de\ntraslado_________ 380.000.-\n\" c Viáticos_________ 200.000.-\n\" e Arriendo de\nbienes raíces____ 80.000.-\n\" f-1-a Pasajes y fletes\nen la Empresa de\nlos Ferrocarriles\ndel Estado_______ 255.000.-\n\" f-1-b Pasajes por vapor 100.000.-\n\" f-2 Pasajes y fletes\nen empresas\nprivadas_________ 60.000.-\n\" g Materiales y\nartículos de\nconsumo__________ 200.000.-\n\" i-2 Forraje__________ 70.000.-\n\" i-3 Vestuario y\nequipo___________ 10.000.-\n\" j Impresos,\nimpresiones y\npublicaciones____ 100.000.-\n\" k Gastos generales\nde oficina_______ 40.000.-\n\" l Conservación y\nreparaciones_____ 180.000.-\n\" m Mantenimiento de\nvehículos\nmotorizados______ 335.927.-\n\" v-2 Imprevistos______ 15.000.-\n\" z Construcciones\nmenores__________30.000.-2.055.927.-\n________\nDirección General de Servicios\nEléctricos y de Gas.\n04/08/04/c Viáticos_________ 15.000.-\n\" e Arriendo de\nbienes raíces____ 34.200.-\n\" f-1-a Pasajes por\nferrocarriles____ 15.000.-\n\" f-2 Pasajes y fletes\nen empresas\nprivadas_________ 8.000.-\n\" g Materiales y\nartículos de\nconsumo__________ 10.000.-\n\" k Gastos generales\nde oficina_______ 3.000.-\n\" l Conservación y\nreparaciones_____ 68.700.- 153.900.-\n_________\nDirección General de Agua Potable\ny Alcantarillado:\n04/10/04/c-2 Aporte patronal $ 15.000.-\n04/10/04/g Materiales y\nartículos de\nconsumo__________ 86.000.-\n04/10/04/j-l Rancho o\nalimentación____ 20.000.-\n04/10/04/i-2 Forraje__________ 80.000.-\n04/10/04/r-3 Vestuario y\nequipo___________ 10.000.-\n04/10/04/j Impresos,\nimpresiones y\npublicaciones____ 20.000.-\n04/10/04/k Gastos generales\nde oficina_______ 50.000.-\n04/10/04/l 1 Conservación y\nreparaciones_____ 200.000.-\n04/10/04/m Mantenimiento de\nvehículos\nmotorizados______ 128.100.-\n04/10/04/v 2 Imprevistos______ 30.000.-\n04/10/11/a-3 Gastos de\nfuncionamiento\nPlanta Elevadora\nde Concón________ 200.000.-$839.100.-\n_________\nMINISTERIO DE RELACIONES EXTERIORES\nSubsecretaría:\n05/01/04/f-2 Pasajes y fletes\nen empresas\nprivadas_________ 621.020.-\n05/01/04/g Materiales y\nartículos de\nconsumo__________\n05/01/04/m Mantenimiento de\nvehículos\nmotorizados______ 47.750.-\n05/01/04/v-3 Imprevistos______ 155.640.-$824.410.-\n_________\nServicio Exterior (Presupuesto oro):\n05/02/04/b-5 Asignación por\ncosto de vida al\npersonal\ndiplomático y\nconsular (oro\n30.000)__________ 120.000.-\n\" c Viáticos (oro\n30.000)__________ 120.000.-\n\" f-2-1 Para gastos de\nviaje de los\nempleados\ndiplomáticos y\nconsulares (oro\n739.865)______2.959.460.-$3.109.460.-\nMINISTERIO DE HACIENDA\nSubsecretaría:\n06/01/04/f-2 Pasajes y fletes\nen empresas\nprivadas_________ 5.000.-\n\" j Impresos,\nimpresiones y\npublicaciones____ 30.000.-\n\" k Gastos generales\nde oficina_______ 10.000.-\n\" l Conservación y\nreparaciones____ 40.000.-\n\" m Mantenimiento de\nvehículos\nmotorizados______ 30.000.-\n\" r-2 Agua y teléfonos_ 30.000.-$145.000.-\n_________\nOficina del Presupuesto:\n06/02/04/l Conservación y\nreparaciones_____ 800.-$ 800.-\n_________\nSUPERINTENDENCIA DE ADUANAS\nServicios de Aduana:\n06/05/04/b-2 Para pagar la\nasignación\nfamiliar y de\ncasa a los\nobreros a jornal_ 60.000.-\n\" f-1-a Pasajes por\nferrocarril______ 60.000.-\n\" f-1-b Pasajes por vapor 20.000.-\n\" f-2 Pasajes y fletes\nen empresas\nprivadas_________ 20.000.-\n\" j Impresos,\nimpresiones y\npublicaciones____ 40.000.- 200.000.-\n_________\nServicio de Explotación de Puertos:\n06/05/04/d-1 Pago de jornales 8.500.000.-\n06/05/04/v-1 Para imprevistos\ny sobretiempo del\npersonal_____1.500.000.-$10.000.000.-\n_________\nTesorería General de la República:\n06/06/04/v-2 Para remunerar a\nlas personas que\nreemplazan\ntransitoriamente\nal personal\nacogido a la ley\nde medicina\npreventiva_______ 115.000.- 115.000.-\n_________\nSuperintendencia de la Casa de Moneda\ny Especies Valoradas\n06/07/02/e Asignación\nfamiliar_________ 10.000.-\n06/07/04/d Jornales_______1.250.000.-1.260.000.-\n___________\nSuperintendencia de Cías. de Seguros:\n06/10/02/a Por años de\nservicios________ 1.250-\n\" e Asignación\nfamiliar_________ 3.960.-\n06/10/04/v-1 Imprevistos______ 30.790.- 36.000.-\n_________\nMINISTERIO DE EDUCACION PUBLICA\nSubsecretaría\n07/01/04/v-13 Para dar\ncumplimiento al\nconvenio\ncelebrado por el\nMinisterio de\nEducación\nPública y la\nInter-American\nEducational\nFoundation,\naprobado por\ndecreto N.o\n1,674, de\n2-IV-1945, cuota\ncorrespondiente a\n1947__________1.020.000.- 1.020.000.-\n___________\nEducación Primaria:\n07/02/04/i-1 Rancho o\nalimentación__1.500.000.- 1.500.000.-\n___________\nEducación Secundaria:\n07/03/04/b-1 Asignación de\ntraslado_________ 100.000.-\n\" c Viáticos_________ 15.000.-\n\" f-l-a Pasajes por\nferrocarril______ 50.000.-\n\" i-1 Rancho o\nalimentación_____ 145.000.-\n\" v-4 Para pago\nprofesores\nsuplentes________ 30.000.-\n07/03/09/e-29 Para pagar becas\nen otros\nestablecimientos_ 30.000.- 370.000.-\n_________\nEnseñanza Profesional:\n07/04/04/i-1 Rancho o\nalimentación_____ 718.071.- 718.071.-\n_________\nMINISTERIO DE JUSTICIA\nSubsecretaría:\n08/01/04/f-2 Pasajes y fletes\nen empresas\nprivadas_________$ 10.000.-\n08/01/04/g Materiales y\nartículos de\nconsumo__________ 15.000.-\n\" j Impresos,\nimpresiones y\npublicaciones____ 50.000.-\n\" m mantenimiento de\nvehículos\nmotorizados______ 10.000.-\n\" v-2 Para pago de\nsuplencias en\nel Poder Judicial 185.000.-\n\" v-6 Para reembolsar\npasajes y fletes\ninvertidos\nde su propio\npeculio por el\npersonal\ndependiente del\nMinisterio_______ 10.000.-$580.000.-\n_________\nJuzgados de Letras de Mayor\nCuantía:\n08/03/04/c Viáticos________$ 40.000.-\n\" e-1 Arriendo de\nlocales, Corte de\nApelaciones y\nJuzgados de\nLetras de Mayor\nCuantía y otras\nreparticiones\njudiciales_______ 30.000.-\n\" g Materiales y\nartículos de\nconsumo__________ 50.000.-\n\" k Gastos generales\nde oficina_______ 10.000.-$130.000.-\n_________\nDirección General del Registro\nCivil Nacional:\n08/05/04/g Materiales y\nartículos de\nconsumo_________$ 150.000.-\n\" v-1 Para sueldos de\noficiales civiles\nadjuntos_________ 650.000.-$800.000.-\n_________\nInstituto Médico Legal Dr. Carlos Ibar:\n08/07/04/g Materiales y\nartículos de\nconsumo__________$ 2.000.-\n\" j Impresos,\nimpresiones y\npublicaciones____ 4.000.-\n\" k Gastos generales\nde oficina_______ 3.000.-\n\" m Mantenimiento de\nvehículos\nmotorizados______ 20.000.-\n\" v-1 Lavado de ropa,\nconfección y\ncompostura de la\nmisma____________ 1.000.-$ 30.000.-\n_________\nDirección General de Prisiones:\n08/08/04/i-1 Rancho o\nalimentación__1.710.000.-$1.710.000.-\n___________\nMINISTERIO DE DEFENSA NACIONAL\nSubsecretaría de Guerra:\n09/01/02/b Por residencia en\nciertas zonas___ $ 43.407.-\n\" e Asignación\nfamilar__________ 843.023.-\n\" f-1 Gratificación de\nalojamiento______ 189.752.-\n\" f-6 Asignación para\npérdidas de Caja 2.000.-\n\" f-7 Asignación de\nalféreces y\nsubtenientes para\nproveerse de\nvestuario________ 34.184.-\n09/01/04/b-1 Indemnización\npor cambio de\nguarnición_______ 350.000.-\n\" b-2 Gratificación de\nzona del personal\ncivil contratado\ny asistentes\nmozos____________ 44.352.-\n\" b-7 Quinquenios\npersonal a\ncontrata_________ 6.600.-\n\" d-1 Jornales\nArsenales de\nGuerra___________ 168.627.-\n\" d-8 Quinquenios\npersonal a\njornal___________ 250.000.-\n\" d-9 Asignación\nfamiliar\npersonal a jornal 120.000.-\n\" i-1-1 Alimentación del\npersonal del\nEjército\ninclusive\nporción\ncomplementaria__6.697.662.-\n09/01/04-i-3 Vestuario y\nequipo___________ 375.000.-\n\" f-1-a Pasajes por\nferrocarril______ 400.000.-\n\" f-2 Pasajes y fletes\nen empresas\nprivadas_________ 300.000.-\n\" r-1 Electricidad y\ngas______________ 500.000.-\n\" r-2 Agua y teléfonos_ 300.000.-\n\" v-1 Haberes y\nviáticos\nrezagados_______1.500.000.-\n\" v-12 Educación\nfísica del\nEjército_________ 50.000.-\n\" w-1 Adquisiciones\ninventariables__19.563.-$12.194.770.-\n________\nSubsecretaría de Marina:\n10/01/02/b Por residencia en\nciertas zonas\n(Antártica)_____$256.000.-\n10/01/04/c-1 Viáticos\nSubsecretaría____ 10.000.-\n\" c-2 Viáticos\npersonal Armada__ 118.000.-\n\" b-1 Cambio de\nresidencia______1.250.000.-\n\" d-4 Asignación\nfamiliar personal\na jornal_________ 568.000.-\n\" f-2-2 Pasajes y fletes\nen empresas\nprivadas,\nServicios\ngenerales de la\nArmada__________1.738.000.-\n\" g-1 Materiales y\nartículos de\nconsumo\nSubsecretaría____ 20.000.-\n\" g-3 Adquisición de\ncarbón\n(Expedición\nAntártica),\nPetróleo y\nMeteriales______1.154.000.-\n\" i-1-1 Rancho\n(Expedición\nAntártica)_______ 300.000.-\n\" i-1-1 Rancho en\nespecies________2.326.000.-\n10/01/04/i-3-2 Vestuario\n(Expedición\nAntártica)_______ 50.000.-\n\" j-1 Impresos,\nimpresiones y\npublicaciones\nSubsecretaría____ 10.000.-\n\" k-1 Gastos generales\nSubsecretaría____ 10.000.-\n\" l-1 Conservación y\nreparaciones\nSubsecretaría____ 20.000.-\n\" v-10 Para gastos\nreservados\nComandancia en\nJefe y Estado\nMayor____________ 40.000.-\n\" v-11 Imprevistos\n(Expedición\nAntártica)_______ 290.000.-\n\" w Adquisiciones\n(Expedición\nAntártica)______250.000.-$8.410.000.-\n_________\nSubsecretaría de Aviación\n11/01/02/a-2 Quinquenios\npersonal de la\nFACH____________$ 627.000.-\n\" e Por especialidad\nen ciertos\nservicios________ 100.000.-\n\" e Asignación\nfamiliar________1.558.000.-\n\" f-1 Gratificación\nde alojamiento___ 191.000.-\n\" f-4 Asignación de\nvestuario\npersonal de tropa 456.000.-\n\" f-5 Gratificación de\nembarcado________ 10.000.-\n\" f-7 Diferencia de\nsueldos personal\nSubsecretaría,\nartículo 12. ley\nN.o 6,915________ 100.000.-\n11/01/04/b-1 Cambio de\nguarnición_______ 400.000.-\n\" f-2 Pasajes y fletes\nen empresas\nprivadas________1.181.000.-\n\" p-2 Hospitalización,\nfunerales e\nindemnización de\naccidentados o\nfallecidos en\nactos de\nservicio,\npatentes\nmunicipales, etc_ 400.000.-\n\" v-2 Gastos\nreservados______100.000.-$5.123.000.-\n_________\nMINISTERIO DE OBRAS PUBLICAS Y VIAS DE\nCOMUNICACION\nSubsecretaría\n12/01/04 d Jornales_________ $ 5.000.-\n\" f-1 Pasajes y fletes\nen la Empresa de\nlos FF. CC. del\nEstado___________ 77.500.-\n\" g Materiales y\nartículos de\nconsumo__________ 50.000.-\n\" j Impresos,\nimpresiones y\npublicaciones____ 40.000.-\n\" k Gastos generales\nde oficina_______ 10.000.-\n\" l Conservación y\nreparaciones_____ 10.000.-\n\" m Mantenimiento de\nvehículos\nmotorizados______ 30.000.-\n\" v-1 Imprevistos______ 5.000.-$227.500.-\n_________\nInspección Superior de Ferrocarriles\n12/02/04 e Viáticos_________ $ 5.000.-\n\" d Jornales_________ 5.000.-\n\" g Materiales y\nartículos de\nconsumo__________ 2.000.-\n\" j Impresos,\nimpresiones y\npublicaciones____ 10.000.-\n\" r Consumos de\nElectricidad,\nAgua, Teléfonos\ny Gas____________ 500.- 22.500.-\n_________\nMINISTERIO DE AGRICULTURA\nSubsecretaría:\n13/01/04 f-1-a Pasajes por\nferrocarril______$ 25.000.- 25.000.-\n__________\nDirección General de Agricultura:\n13/02/04 f-1-a Pasajes por\nferrocarril______$ 75.000.-\n\" i-1-2 Rancho o\nalimentación,\nEnseñanza\nAgrícola_________ 520.000.-\n\" r-1 Electricidad y\nGas______________ 30.000.-\n\" r-2 Agua Potable y\nTeléfonos________ 30.000.- 655.000.-\n_________\nMINISTERIO DE TIERRAS Y COLONIZACION\nDirección General de Tierras:\n14/02/04 e Viáticos_______$ 150.000.-\n\" d-1 Jornales\nDirección\nGeneral__________ 50.000.-\n\" f-1-a Pasajes por\nferrocarril______ 150.000.-\n\" f-1-b Pasajes por vapor 50.000.- 400.000.-\n_________\nMINISTERIO DEL TRABAJO\nSubsecretaría:\n15/01/04 f-1-a Pasajes por\nferrocarriles____$ 64.000.-\n\" f-2 Pasajes y fletes\nen empresas\nprivadas_________ 20.000.-\n\" g Materiales y\nartículos de\nconsumo__________ 6.000.-\n\" j Impresos,\nimpresiones y 12.000.-\npublicaciones____ 5.000.-\n\" k Gastos generales\nde oficina_______\n\" l Conservación y\nrepresentaciones 10.000.-\n\" m Mantenimiento de\nvehículos\nmotorizados______ 25.000.-\n\" r-2 Agua y Teléfonos_ 4.000.- 146.000.-\n_________\nDirección General del Trabajo:\n15/02/04 b Gratificaciones y\npremios__________$ 29.000.-\n\" c Viáticos_________ 30.525.-\n\" f-2 Pasajes y fletes\nen empresas\nprivadas_________ 40.000.-\n\" g Materiales y\nartículos de\nconsumo__________ 20.000.-\n\" j Impresos,\nimpresiones y\npublicaciones____ 20.000.-\n\" k Gastos generales\nde Oficina_______ 40.000.-\n\" l Conservación y\nreparaciones_____ 20.000.-\n\" m Mantenimiento de\nvehículos\nmotorizados______ 25.000.-\n\" r-1 Electricidad y\nGas______________ 30.000.-\n\" r-2 Teléfonos y Agua\nPotable__________ 60.000.- 314.525.-\n_________\nMINISTERIO DE SALUBRIDAD, PREVISION Y ASISTENCIA\nSOCIAL\nSubsecretaría.\n16/01/04 f-1-a Pasajes por\nferrocarril______$ 60.000.-\n\" g Materiales y\nartículos de\nconsumo__________ 15.000.-\n\" j Impresos,\nimpresiones y\npublicaciones____ 15.000.-\n\" m Mantenimiento de\nvehículos\nmotorizados______ 15.000.-\n\" v-2 Para necesidades\neventuales del\nMinisterio y\nservicios\ndependientes_____ 139.300.-\n\" v-4 Para atender a los\ngastos del\nCongreso de\nNeurocirugía_____ 84.553.-\n16/01/09 f-IV-47 Para el\nDepartamento de\nMedicina\nExperimental\ndependiente de la\nDirección\nGeneral de\nSanidad__________ 60.000.- 338.853.-\n_________\nDirección General de Sanidad:\n16/02/04 v-1 Para imprevistos_$ 85.000.-\n\" v-5 Para atender los\ngastos que\ndemanden las\ncampañas contra\nenfermedades\ninfectocontagiosas 100.000.-\n\" v-9 Para atender a\nlos gastos\nque demande\nla campaña\nantivenérea______ 440.000.-\n\" v-10 Para las unidades\nsanitarias de\nAntofagasta,\nValparaíso,\nConcepción y\nTemuco___________ 200.000.- 825.000.-\n_________\nDirección General de Protección a la\nInfancia y Adolescencia:\n16/03/04 f-1-a Pasajes por\nferrocarril______$ 20.000.-\n\" g Materiales y\nartículos de\nconsumo__________ 280.000.-\n\" j Impresos,\nimpresiones y\npublicaciones____ 90.000.-\n\" k Gastos generales\nde oficina_______ 60.000.-\n\" l Conservación y\nreparaciones_____ 30.000.-\n\" w Adquisiciones____ 60.000.- 540.000.-\n_________\nDirección General de Previsión\nSocial:\n16/05/04 b Gratificaciones y\npremios__________$ 5.000.-\n\" k Gastos generales\nde oficina_______ 2.000.-\n\" v Varios e\nImprevistos______ 430.000.- 437.000.-\n_________\nMINISTERIO DE ECONOMIA Y COMERCIO\nDepartamento de Minas y Petróleos:\n17/03/04 k Gastos generales\nde oficina_______ $ 4.000.- 4.000.-\n_________\nDepartamento de Pesca y Caza:\n17/04/04 c Viáticos_________ $ 8.000.-\n\" d Jornales_________ 12.000.- 20.000.-\n_________\nDirección General de Estadísticas:\n17/05/04 c Viáticos_________$ 50.000.-\n\" d Jornales_________ 24.000.-\n\" f-1-a Pasajes por\nferrocarril______ 20.000.-\n\" g Materiales y\nartículos de\nconsumo__________ 10.000.-\n\" k Gastos generales\nde oficina_______ 3.000.-\n\" r-2 Agua Potable y\nTeléfonos________ 5.000.-\n\" w Adquisiciones____ 65.000.- 177.000.-\n_________\nComisariato General de Subsistencias\ny Precios:\n17/06/02 e Asignación\nfamiliar_________$ 50.000.-\n17/06/04 e Arriendo de\nbienes raíces____ 62.000.- 112.000.-\n____________\nTOTAL____________ $ 68.608.209.-"
    },
    {
      "provision_ref": "art2",
      "section": "2",
      "title": "Artículo 2",
      "content": "Artículo 2.o Las cantidades que no se alcancen a invertir, autorizadas por la presente ley, se contabilizarán en \"Obligaciones por cumplir\"."
    },
    {
      "provision_ref": "art3",
      "section": "3",
      "title": "Artículo 3",
      "content": "Artículo 3.o Los fondos consultados en la presente ley sólo podrán ser invertidos en pago de compromisos contraídos en el año 1947."
    },
    {
      "provision_ref": "art4",
      "section": "4",
      "title": "Artículo 4",
      "content": "Artículo 4.o La aprobación de los traspasos contenidos en la presente ley no exime de responsabilidad ni libera de las sanciones que correspondan con arreglo a las leyes y reglamentos vigentes, a los funcionarios que hubieren autorizado gastos que excedan a los consultados en la Ley de Presupuestos, sin solicitar previamente de sus superiores la tramitación de la autorización legislativa correspondiente."
    },
    {
      "provision_ref": "art5",
      "section": "5",
      "title": "Artículo 5",
      "content": "Artículo 5.o Esta ley regirá desde su publicación en el Diario Oficial."
    }
  ],
  "definitions": []
}