{
  "id": "cl-leychile-norma-27458",
  "type": "statute",
  "title": "AUTORIZA AL PRESIDENTE DE LA REPUBLICA PARA DESTINAR\nEL PREDIO FISCAL QUE INDICA Y CUYOS DESLINDES SEÑALA,\nUBICADO EN LA LOCALIDAD DE SARMIENTO, COMUNA DE ROMERAL,\nPARA LA CONSTRUCCION DE UN RETEN DE CARABINEROS.",
  "short_name": "Ley 13378",
  "status": "in_force",
  "issued_date": "1959-08-27",
  "in_force_date": "1959-09-12",
  "url": "https://www.bcn.cl/leychile/navegar?idNorma=27458",
  "provisions": [
    {
      "provision_ref": "artunico",
      "section": "UNICO",
      "title": "Artículo UNICO",
      "content": "\"Artículo único. Autorízase al Presidente de la República para que destine a la construcción de un Retén de Carabineros, el predio fiscal ubicado en la localidad de Sarmiento, comuna de Romeral, del departamento y provincia de Curicó, de una superficie de mil setecientos ochenta metros cuadrados y que deslinda: Norte, Segundo Bastías; Sur, Camino vecinal; Oriente, Fidelisa Bastías y Agustín González y Poniente, Francisco Javier Silva.\nEste terreno se encuentra inscrito a nombre del Fisco a fojas 389, N° 593, del Registro de Propiedad del año 1957, del Conservador de Bienes Raíces de Curicó\"."
    }
  ],
  "definitions": []
}