{
  "id": "cl-leychile-norma-23612",
  "type": "statute",
  "title": "CONCEDE UN SUPLEMENTO AL PRESUPUESTO DE MARINA PARA LA CONSTRUCCION DEL NUEVO DIQUE DE TALCAHUANO",
  "short_name": "Ley 2941",
  "status": "in_force",
  "issued_date": "1914-10-28",
  "in_force_date": "1914-10-29",
  "url": "https://www.bcn.cl/leychile/navegar?idNorma=23612",
  "provisions": [
    {
      "provision_ref": "artunico",
      "section": "UNICO",
      "title": "Artículo UNICO",
      "content": "ARTICULO UNICO.- Concédese un suplemento de seiscientos mil pesos ($ 600,000), oro de dieciocho peniques al ítem 846 del Presupuesto de Marina, para atender a la construccion del nuevo Dique de Talcahuano.\nEstos fondos se sacarán de los autorizados por la lei número 2,319 de 5 de Julio de 1910 para adquisiciones navales."
    }
  ],
  "definitions": []
}