{
  "id": "cl-leychile-norma-1144000",
  "type": "statute",
  "title": "PRORROGA LA FECHA DE RENOVACIÓN DE LAS REVISIONES TÉCNICAS",
  "short_name": "Ley 21224",
  "status": "in_force",
  "issued_date": "2020-03-31",
  "in_force_date": "2020-04-01",
  "url": "https://www.bcn.cl/leychile/navegar?idNorma=1144000",
  "provisions": [
    {
      "provision_ref": "artunico",
      "section": "único",
      "title": "Artículo único",
      "content": "\"Artículo único.- Prorrógase, a partir de la publicación de la presente ley y hasta el 30 de junio del año 2020, la vigencia de las revisiones técnicas de vehículos cuyo vencimiento haya ocurrido a partir del mes de octubre del año 2019. El Ministerio de Transportes y Telecomunicaciones, en uso de sus atribuciones, establecerá el calendario y los dígitos correspondientes, a objeto de organizar, en lo sucesivo, la realización de dicho trámite.\"."
    }
  ],
  "definitions": []
}