{
  "id": "cl-leychile-norma-258920",
  "type": "statute",
  "title": "CONCECE A DOÑA SECUNDINA CASTRO VDA. DE VERGARA UNA PENSION MENSUAL CUYO MONTO INDICA",
  "short_name": "Ley 10727",
  "status": "in_force",
  "issued_date": "1952-10-09",
  "in_force_date": "1952-11-05",
  "url": "https://www.bcn.cl/leychile/navegar?idNorma=258920",
  "provisions": [
    {
      "provision_ref": "artunico",
      "section": "UNICO",
      "title": "Artículo UNICO",
      "content": "Artículo único. Concédese, por gracia, a doña Secundina Castro Jeria viuda de Vergara una pensión de $ 1.000 mensuales.\nEl gasto que significa esta ley se imputará al ítem de pensiones del Presupuesto del Ministerio de Hacienda."
    }
  ],
  "definitions": []
}